{
    "FromExName": "HUOBI",
    "ToExName": "WKJ",
    "NotifyEmail": "1257378235@qq.com",
    "StepSeconds": 2,
    "FromTarCoin": "eos",
    "FromBaseCoin": "usdt",
    "FromDepositAddress": "huobideposit",
    "FromDepositMemo": "4775185",
    "FromWithdrawChain": "eos1",
    "ToTarCoin": "eos",
    "ToBaseCoin": "bitcny",
    "ToDepositAddress": "wankejia2222",
    "ToDepositMemo": "000000041543636665",
    "ToWithdrawChain": "",
    "MinBalanceRatio": 2,
    "MaxAmount": 10,
    "MinAmount": 0.1,
    "ToWithDrawAmount": 600,
    "FromWithDrawAmount": 1000,
    "ToNeedDepositAmount": 1500,
    "FromNeedDepositAmount": 1500,
    "ToWithDrawAmountLimit": 2500,
    "FromWithDrawAmountLimit": 2500,
    "ToBuyProfit": 0.001,
    "ToSellProfit": 0.001,
    "FromUsdt2Cny": true,
    "ToUsdt2Cny": false,
    "MinMoney": 39.99,
    "ProfitStep": 0.002,
    "MaxOrders": 1,
    "UpdateConfigSeconds": 40,
    "UsdtConvertExName": "WKJ",
    "ConfigStatus": "decoded",
    "WithdrawAddAmount": 0.001
}